CHANGES.txt
COPYRIGHT.txt
LICENSE.txt
README.txt
bootstrap.py
buildout.cfg
setup.py
src/z3c/__init__.py
src/z3c.viewtemplate.egg-info/PKG-INFO
src/z3c.viewtemplate.egg-info/SOURCES.txt
src/z3c.viewtemplate.egg-info/dependency_links.txt
src/z3c.viewtemplate.egg-info/namespace_packages.txt
src/z3c.viewtemplate.egg-info/not-zip-safe
src/z3c.viewtemplate.egg-info/requires.txt
src/z3c.viewtemplate.egg-info/top_level.txt
src/z3c/viewtemplate/README.txt
src/z3c/viewtemplate/__init__.py
src/z3c/viewtemplate/baseview.py
src/z3c/viewtemplate/interfaces.py
src/z3c/viewtemplate/macro.py
src/z3c/viewtemplate/meta.zcml
src/z3c/viewtemplate/pagetemplate.py
src/z3c/viewtemplate/tests.py
src/z3c/viewtemplate/zcml.py