Metadata-Version: 1.0
Name: z3c.viewtemplate
Version: 0.4.1
Summary: View Templates
Home-page: http://cheeseshop.python.org/pypi/z3c.viewtemplate
Author: Zope Corporation and Contributors
Author-email: zope3-dev@zope.org
License: ZPL 2.1
Keywords: zope3 view template pagetemplate macro
Platform: UNKNOWN
Classifier: Development Status :: 5 - Production/Stable
Classifier: Environment :: Web Environment
Classifier: Intended Audience :: Developers
Classifier: License :: OSI Approved :: Zope Public License
Classifier: Programming Language :: Python
Classifier: Natural Language :: English
Classifier: Operating System :: OS Independent
Classifier: Topic :: Internet :: WWW/HTTP
Classifier: Framework :: Zope3
